README.rst
setup.py
sivart.py
sivart.egg-info/PKG-INFO
sivart.egg-info/SOURCES.txt
sivart.egg-info/dependency_links.txt
sivart.egg-info/requires.txt
sivart.egg-info/top_level.txt