Metadata-Version: 1.1
Name: sivart
Version: 0.2.0
Summary: 
